{
  "slo": {
    "max_concurrency": 256,
    "max_prompt_len": 2048,
    "max_output_len": 2048
  },
  "knobs": {
    "kv_reserve_frac": 0.5,
    "headroom_gb": 2.0,
    "headroom_frac": 0.05,
    "prefill_budget_tokens": 16384,
    "group_size": 128
  },
  "vram_breakdown_bytes": {
    "total_bytes": 85899345920,
    "non_moe_bytes": 3082186752,
    "int4_weights_bytes": 15061745664,
    "headroom_bytes": 4294967296,
    "kv_bytes": 51539607552,
    "activations_bytes": 100663296,
    "bf16_budget_bytes": 11820175360,
    "bf16_expert_size_bytes": 9437184,
    "k_heter_experts": 1252,
    "k_total_experts": 6144
  },
  "K_heter_experts": 3072,
  "num_int4_only": 3072,
  "per_layer_counts": {
    "0": {
      "heter": 109,
      "int4_only": 19
    },
    "1": {
      "heter": 0,
      "int4_only": 128
    },
    "2": {
      "heter": 8,
      "int4_only": 120
    },
    "3": {
      "heter": 121,
      "int4_only": 7
    },
    "4": {
      "heter": 47,
      "int4_only": 81
    },
    "5": {
      "heter": 101,
      "int4_only": 27
    },
    "6": {
      "heter": 92,
      "int4_only": 36
    },
    "7": {
      "heter": 56,
      "int4_only": 72
    },
    "8": {
      "heter": 85,
      "int4_only": 43
    },
    "9": {
      "heter": 47,
      "int4_only": 81
    },
    "10": {
      "heter": 79,
      "int4_only": 49
    },
    "11": {
      "heter": 93,
      "int4_only": 35
    },
    "12": {
      "heter": 84,
      "int4_only": 44
    },
    "13": {
      "heter": 88,
      "int4_only": 40
    },
    "14": {
      "heter": 60,
      "int4_only": 68
    },
    "15": {
      "heter": 92,
      "int4_only": 36
    },
    "16": {
      "heter": 92,
      "int4_only": 36
    },
    "17": {
      "heter": 93,
      "int4_only": 35
    },
    "18": {
      "heter": 26,
      "int4_only": 102
    },
    "19": {
      "heter": 94,
      "int4_only": 34
    },
    "20": {
      "heter": 63,
      "int4_only": 65
    },
    "21": {
      "heter": 0,
      "int4_only": 128
    },
    "22": {
      "heter": 70,
      "int4_only": 58
    },
    "23": {
      "heter": 0,
      "int4_only": 128
    },
    "24": {
      "heter": 21,
      "int4_only": 107
    },
    "25": {
      "heter": 0,
      "int4_only": 128
    },
    "26": {
      "heter": 92,
      "int4_only": 36
    },
    "27": {
      "heter": 0,
      "int4_only": 128
    },
    "28": {
      "heter": 82,
      "int4_only": 46
    },
    "29": {
      "heter": 78,
      "int4_only": 50
    },
    "30": {
      "heter": 43,
      "int4_only": 85
    },
    "31": {
      "heter": 0,
      "int4_only": 128
    },
    "32": {
      "heter": 0,
      "int4_only": 128
    },
    "33": {
      "heter": 89,
      "int4_only": 39
    },
    "34": {
      "heter": 108,
      "int4_only": 20
    },
    "35": {
      "heter": 83,
      "int4_only": 45
    },
    "36": {
      "heter": 32,
      "int4_only": 96
    },
    "37": {
      "heter": 88,
      "int4_only": 40
    },
    "38": {
      "heter": 92,
      "int4_only": 36
    },
    "39": {
      "heter": 0,
      "int4_only": 128
    },
    "40": {
      "heter": 90,
      "int4_only": 38
    },
    "41": {
      "heter": 94,
      "int4_only": 34
    },
    "42": {
      "heter": 86,
      "int4_only": 42
    },
    "43": {
      "heter": 91,
      "int4_only": 37
    },
    "44": {
      "heter": 102,
      "int4_only": 26
    },
    "45": {
      "heter": 94,
      "int4_only": 34
    },
    "46": {
      "heter": 0,
      "int4_only": 128
    },
    "47": {
      "heter": 107,
      "int4_only": 21
    }
  },
  "top_scores": [
    {
      "layer": 3,
      "expert": 82,
      "score": 0.01039016625697404
    },
    {
      "layer": 3,
      "expert": 25,
      "score": 0.0016067267407691814
    },
    {
      "layer": 2,
      "expert": 92,
      "score": 0.0014520145800663044
    },
    {
      "layer": 3,
      "expert": 64,
      "score": 0.001124708718538427
    },
    {
      "layer": 47,
      "expert": 39,
      "score": 0.0011091210870847299
    },
    {
      "layer": 47,
      "expert": 80,
      "score": 0.001056662657290182
    },
    {
      "layer": 3,
      "expert": 93,
      "score": 0.0010510670762531728
    },
    {
      "layer": 47,
      "expert": 0,
      "score": 0.0010266864116932973
    },
    {
      "layer": 3,
      "expert": 70,
      "score": 0.0010175936024871483
    },
    {
      "layer": 47,
      "expert": 23,
      "score": 0.001011698288894855
    },
    {
      "layer": 3,
      "expert": 54,
      "score": 0.0009908148234743285
    },
    {
      "layer": 3,
      "expert": 73,
      "score": 0.0009908148234743285
    },
    {
      "layer": 3,
      "expert": 89,
      "score": 0.0009439519602018941
    },
    {
      "layer": 47,
      "expert": 67,
      "score": 0.0009405047056022541
    },
    {
      "layer": 47,
      "expert": 119,
      "score": 0.0009292636135034224
    },
    {
      "layer": 3,
      "expert": 29,
      "score": 0.0009238678759422793
    },
    {
      "layer": 3,
      "expert": 106,
      "score": 0.0009238678759422793
    },
    {
      "layer": 47,
      "expert": 61,
      "score": 0.0008992873679065378
    },
    {
      "layer": 47,
      "expert": 17,
      "score": 0.0008917933065073167
    },
    {
      "layer": 3,
      "expert": 7,
      "score": 0.0008836997074230498
    }
  ],
  "zero_layers": [
    1,
    21,
    23,
    25,
    27,
    32,
    39,
    46
  ]
}